scrmbl/__init__.py
scrmbl/cli.py
scrmbl/main.py
scrmbl-1.0.0.dist-info/entry_points.txt
scrmbl-1.0.0.dist-info/LICENSE
scrmbl-1.0.0.dist-info/WHEEL
scrmbl-1.0.0.dist-info/METADATA
scrmbl-1.0.0.dist-info/RECORD
