Metadata-Version: 2.1
Name: scrmbl
Version: 1.0.0
Summary: Library for scrambled printing in terminal
Home-page: https://github.com/etienne-napoleone/scrmbl
License: MIT
Keywords: print,library,movie,action,scramble
Author: Etienne Napoleone
Author-email: etienne@tomochain.com
Requires-Python: >=3.5,<4.0
Classifier: License :: OSI Approved :: MIT License
Classifier: Programming Language :: Python :: 3
Classifier: Programming Language :: Python :: 3.5
Classifier: Programming Language :: Python :: 3.6
Classifier: Programming Language :: Python :: 3.7
Requires-Dist: click (>=7.0,<8.0)
